accendino/__init__.py
accendino/builditems.py
accendino/localdeps.py
accendino/sources.py
accendino/utils.py
accendino-1.0.0.dist-info/LICENSE.txt
accendino-1.0.0.dist-info/METADATA
accendino-1.0.0.dist-info/WHEEL
accendino-1.0.0.dist-info/entry_points.txt
accendino-1.0.0.dist-info/top_level.txt
accendino-1.0.0.dist-info/RECORD
